docker_volume_download/__init__.py
docker_volume_download/__main__.py
docker_volume_download/config.py
docker_volume_download-0.1.0.dist-info/METADATA
docker_volume_download-0.1.0.dist-info/WHEEL
docker_volume_download-0.1.0.dist-info/entry_points.txt
docker_volume_download-0.1.0.dist-info/RECORD
