Metadata-Version: 2.4
Name: docker_volume_download
Version: 0.1.0
Summary: A tool to download Docker volumes and upload it on to Google Drive.
Author-email: Pyae Sone Hein <pyaesonehein81998@gmail.com>
License: MIT
Requires-Python: >=3.8
Requires-Dist: docker>=7.1.0
Requires-Dist: pydrive2>=1.21.3
